{
  "leaseParams": {
    "totalAllowedKm": 30000,
    "costPerExtraKm": 0.1815,
    "leaseDurationMonths": 36,
    "leaseStartDate": "2025-07-29",
    "startingMileage": 34593
  },
  "mileageEntries": [
    {
      "id": 1760274189760,
      "date": "2025-10-12",
      "mileage": 37117
    },
    {
      "id": 1760294817740,
      "date": "2025-08-31",
      "mileage": 35173
    },
    {
      "id": 1760295142999,
      "date": "2025-08-05",
      "mileage": 34893
    },
    {
      "id": 1760514789932,
      "date": "2025-10-15",
      "mileage": 37154
    },
    {
      "id": 1760567150397,
      "date": "2025-10-15",
      "mileage": 37185
    },
    {
      "id": 1761291405317,
      "date": "2025-10-24",
      "mileage": 37275
    },
    {
      "id": 1761724829602,
      "date": "2025-10-29",
      "mileage": 37378
    },
    {
      "id": 1761857403006,
      "date": "2025-10-30",
      "mileage": 37711
    },
    {
      "id": 1762194665002,
      "date": "2025-11-03",
      "mileage": 37752
    },
    {
      "id": 1762545448768,
      "date": "2025-11-07",
      "mileage": 37804
    },
    {
      "id": 1762888144074,
      "date": "2025-11-11",
      "mileage": 37834
    },
    {
      "id": 1763058424487,
      "date": "2025-11-13",
      "mileage": 37870
    }
  ],
  "lastUpdated": "2025-11-13T18:27:04.587Z"
}